tdash/__init__.py
tdash/components.py
tdash/core.py
tdash/dashboard.py
tdash/nav.py
tdash/properties.py
thrill_dash-0.4.0.dist-info/METADATA
thrill_dash-0.4.0.dist-info/WHEEL
thrill_dash-0.4.0.dist-info/top_level.txt
thrill_dash-0.4.0.dist-info/RECORD
