Metadata-Version: 2.1
Name: thrill-dash
Version: 0.4.0
Summary: A Dash library with various components to make working with Dash easier
Home-page: https://github.com/mitchelllisle/thrill-dash-lib
Author: Mitchell Lisle
Author-email: m.lisle90@gmail.com
License: UNKNOWN
Keywords: tdash
Platform: UNKNOWN
Requires-Dist: dash
Requires-Dist: dash-bootstrap-components
Requires-Dist: funcy
